tusfilter.py
tusfilter-0.5.1.dist-info/DESCRIPTION.rst
tusfilter-0.5.1.dist-info/METADATA
tusfilter-0.5.1.dist-info/RECORD
tusfilter-0.5.1.dist-info/WHEEL
tusfilter-0.5.1.dist-info/metadata.json
tusfilter-0.5.1.dist-info/top_level.txt
