Metadata-Version: 2.0
Name: tusfilter
Version: 0.5.1
Summary: python wsgi filter for tus protocol 1.0.0
Home-page: https://github.com/everydo/tusfilter
Author: easydo.cn
Author-email: info@easydo.cn
License: MIT
Keywords: tus wsgi filter
Platform: UNKNOWN
Classifier: Development Status :: 3 - Alpha
Classifier: Programming Language :: Python :: 2
Classifier: Programming Language :: Python :: 2.7
Classifier: Programming Language :: Python :: 3
Classifier: Programming Language :: Python :: 3.5
Classifier: Topic :: Internet :: WWW/HTTP
Classifier: Topic :: Internet :: WWW/HTTP :: WSGI
Classifier: Topic :: Internet :: WWW/HTTP :: WSGI :: Middleware
Classifier: License :: OSI Approved :: MIT License
Requires-Dist: WebOb
